spycy/__init__.py
spycy/curry.py
spycy/utils.py
spycy-0.2.dist-info/DESCRIPTION.rst
spycy-0.2.dist-info/METADATA
spycy-0.2.dist-info/RECORD
spycy-0.2.dist-info/WHEEL
spycy-0.2.dist-info/metadata.json
spycy-0.2.dist-info/top_level.txt
